spherical_geometry/__init__.py
spherical_geometry/_version.py
spherical_geometry/graph.py
spherical_geometry/great_circle_arc.py
spherical_geometry/math_util.cp312-win32.pyd
spherical_geometry/polygon.py
spherical_geometry/vector.py
spherical_geometry/tests/__init__.py
spherical_geometry/tests/helpers.py
spherical_geometry/tests/test_basic.py
spherical_geometry/tests/test_intersection.py
spherical_geometry/tests/test_union.py
spherical_geometry/tests/data/1904-66_TAN.fits.gz
spherical_geometry/tests/data/1904-77_TAN.fits.gz
spherical_geometry/tests/data/2chipA.fits.gz
spherical_geometry/tests/data/2chipB.fits.gz
spherical_geometry/tests/data/2chipC.fits.gz
spherical_geometry/tests/data/almost_same_polygons.npz
spherical_geometry/tests/data/difficult_intersections.txt
spherical_geometry/tests/data/j8bt06nyq_flt.fits
spherical_geometry-1.3.3.dist-info/LICENSE.rst
spherical_geometry-1.3.3.dist-info/METADATA
spherical_geometry-1.3.3.dist-info/QD_LIBRARY_LICENSE.rst
spherical_geometry-1.3.3.dist-info/WHEEL
spherical_geometry-1.3.3.dist-info/top_level.txt
spherical_geometry-1.3.3.dist-info/RECORD
