Metadata-Version: 2.2
Name: spherical_geometry
Version: 1.3.3
Summary: Python based tools for spherical geometry
Author-email: STScI <help@stsci.edu>
License: BSD-3-Clause
Project-URL: bug, https://github.com/spacetelescope/spherical_geometry/issues/
Project-URL: source, https://github.com/spacetelescope/spherical_geometry/
Project-URL: help, https://hsthelp.stsci.edu
Project-URL: documentation, http://spherical-geometry.readthedocs.io/
Keywords: astronomy,astrophysics,space,science,spherical,geometry
Classifier: Intended Audience :: Science/Research
Classifier: License :: OSI Approved :: BSD License
Classifier: Operating System :: OS Independent
Classifier: Programming Language :: C
Classifier: Programming Language :: Python :: 3
Classifier: Programming Language :: Python :: Implementation :: CPython
Classifier: Topic :: Scientific/Engineering :: Astronomy
Classifier: Topic :: Scientific/Engineering :: Physics
Requires-Python: >=3.11
License-File: licenses\LICENSE.rst
License-File: licenses\QD_LIBRARY_LICENSE.rst
Requires-Dist: numpy>=1.25
Requires-Dist: astropy>=5.2.0
Provides-Extra: test
Requires-Dist: pytest; extra == "test"
Requires-Dist: pytest-astropy-header; extra == "test"
Provides-Extra: docs
Requires-Dist: sphinx-automodapi; extra == "docs"
Requires-Dist: numpydoc; extra == "docs"
